mx/__init__.py
mx/collector.py
mx/DateTime/Feasts.py
mx/DateTime/__init__.py
mx/DateTime/mx_datetime.py
mx/DateTime/mx_datetimedelta.py
mx/DateTime/mx_relativedatetime.py
tests/__init__.py
tests/test_datetime.py
tests/test_datetimedelta.py
tests/test_datetimedeltafrom.py
tests/test_datetimefrom.py
tests/test_feasts.py
tests/test_relativedatetime.py
tests/test_relativedatetimediff.py
MxDateTimeWrap-2.0.dist-info/METADATA
MxDateTimeWrap-2.0.dist-info/WHEEL
MxDateTimeWrap-2.0.dist-info/top_level.txt
MxDateTimeWrap-2.0.dist-info/RECORD
