Metadata-Version: 2.1
Name: MxDateTimeWrap
Version: 2.0
Summary: Wrap mx.DateTime functions using native datetime
Home-page: http://www.trackwell.com/
Author: Sindri (Trackwell hf.)
Author-email: sindri@trackwell.com
License: UNKNOWN
Platform: UNKNOWN
Classifier: Development Status :: 5 - Production/Stable
Classifier: Topic :: Utilities
Classifier: Intended Audience :: Developers
Classifier: Programming Language :: Python :: 2
Classifier: Programming Language :: Python :: 3
Requires-Dist: six
Requires-Dist: holidays
